[
  {
    "Champion_Name": "Ivern",
    "Champion_Rank": "1",
    "Date_Scraped": "2017-03-30",
    "Number_of_Games": "1,303",
    "Win_Percentage": "54.03%"
  },
  {
    "Champion_Name": "Skarner",
    "Champion_Rank": "2",
    "Date_Scraped": "2017-03-30",
    "Number_of_Games": "499",
    "Win_Percentage": "53.91%"
  },
  {
    "Champion_Name": "Blitzcrank",
    "Champion_Rank": "3",
    "Date_Scraped": "2017-03-30",
    "Number_of_Games": "5,951",
    "Win_Percentage": "53.69%"
  },
  {
    "Champion_Name": "Shaco",
    "Champion_Rank": "4",
    "Date_Scraped": "2017-03-30",
    "Number_of_Games": "3,980",
    "Win_Percentage": "53.42%"
  },
  {
    "Champion_Name": "Swain",
    "Champion_Rank": "5",
    "Date_Scraped": "2017-03-30",
    "Number_of_Games": "2,244",
    "Win_Percentage": "53.39%"
  },
  {
    "Champion_Name": "Wukong",
    "Champion_Rank": "6",
    "Date_Scraped": "2017-03-30",
    "Number_of_Games": "2,063",
    "Win_Percentage": "53.17%"
  },
  {
    "Champion_Name": "Yorick",
    "Champion_Rank": "7",
    "Date_Scraped": "2017-03-30",
    "Number_of_Games": "1,138",
    "Win_Percentage": "52.64%"
  },
  {
    "Champion_Name": "Zac",
    "Champion_Rank": "8",
    "Date_Scraped": "2017-03-30",
    "Number_of_Games": "2,211",
    "Win_Percentage": "52.51%"
  },
  {
    "Champion_Name": "Xin Zhao",
    "Champion_Rank": "9",
    "Date_Scraped": "2017-03-30",
    "Number_of_Games": "3,869",
    "Win_Percentage": "52.42%"
  },
  {
    "Champion_Name": "Xerath",
    "Champion_Rank": "10",
    "Date_Scraped": "2017-03-30",
    "Number_of_Games": "1,205",
    "Win_Percentage": "52.37%"
  },
  {
    "Champion_Name": "Janna",
    "Champion_Rank": "11",
    "Date_Scraped": "2017-03-30",
    "Number_of_Games": "2,785",
    "Win_Percentage": "52.28%"
  },
  {
    "Champion_Name": "Illaoi",
    "Champion_Rank": "12",
    "Date_Scraped": "2017-03-30",
    "Number_of_Games": "1,413",
    "Win_Percentage": "52.02%"
  },
  {
    "Champion_Name": "Ziggs",
    "Champion_Rank": "13",
    "Date_Scraped": "2017-03-30",
    "Number_of_Games": "1,967",
    "Win_Percentage": "52.01%"
  },
  {
    "Champion_Name": "Ahri",
    "Champion_Rank": "14",
    "Date_Scraped": "2017-03-30",
    "Number_of_Games": "6,731",
    "Win_Percentage": "51.97%"
  },
  {
    "Champion_Name": "Warwick",
    "Champion_Rank": "15",
    "Date_Scraped": "2017-03-30",
    "Number_of_Games": "4,522",
    "Win_Percentage": "51.95%"
  },
  {
    "Champion_Name": "Veigar",
    "Champion_Rank": "16",
    "Date_Scraped": "2017-03-30",
    "Number_of_Games": "3,215",
    "Win_Percentage": "51.94%"
  },
  {
    "Champion_Name": "Fiddlesticks",
    "Champion_Rank": "17",
    "Date_Scraped": "2017-03-30",
    "Number_of_Games": "1,074",
    "Win_Percentage": "51.77%"
  },
  {
    "Champion_Name": "Sejuani",
    "Champion_Rank": "18",
    "Date_Scraped": "2017-03-30",
    "Number_of_Games": "855",
    "Win_Percentage": "51.70%"
  },
  {
    "Champion_Name": "Soraka",
    "Champion_Rank": "19",
    "Date_Scraped": "2017-03-30",
    "Number_of_Games": "3,089",
    "Win_Percentage": "51.67%"
  },
  {
    "Champion_Name": "Fizz",
    "Champion_Rank": "20",
    "Date_Scraped": "2017-03-30",
    "Number_of_Games": "3,893",
    "Win_Percentage": "51.55%"
  },
  {
    "Champion_Name": "Master Yi",
    "Champion_Rank": "21",
    "Date_Scraped": "2017-03-30",
    "Number_of_Games": "5,149",
    "Win_Percentage": "51.41%"
  },
  {
    "Champion_Name": "Vel'Koz",
    "Champion_Rank": "22",
    "Date_Scraped": "2017-03-30",
    "Number_of_Games": "1,847",
    "Win_Percentage": "51.27%"
  },
  {
    "Champion_Name": "Sona",
    "Champion_Rank": "23",
    "Date_Scraped": "2017-03-30",
    "Number_of_Games": "3,811",
    "Win_Percentage": "51.27%"
  },
  {
    "Champion_Name": "Nami",
    "Champion_Rank": "24",
    "Date_Scraped": "2017-03-30",
    "Number_of_Games": "3,389",
    "Win_Percentage": "51.22%"
  },
  {
    "Champion_Name": "Sion",
    "Champion_Rank": "25",
    "Date_Scraped": "2017-03-30",
    "Number_of_Games": "1,441",
    "Win_Percentage": "51.21%"
  },
  {
    "Champion_Name": "Jarvan IV",
    "Champion_Rank": "26",
    "Date_Scraped": "2017-03-30",
    "Number_of_Games": "1,397",
    "Win_Percentage": "51.18%"
  },
  {
    "Champion_Name": "Nocturne",
    "Champion_Rank": "27",
    "Date_Scraped": "2017-03-30",
    "Number_of_Games": "1,081",
    "Win_Percentage": "51.16%"
  },
  {
    "Champion_Name": "Teemo",
    "Champion_Rank": "28",
    "Date_Scraped": "2017-03-30",
    "Number_of_Games": "3,634",
    "Win_Percentage": "50.91%"
  },
  {
    "Champion_Name": "Draven",
    "Champion_Rank": "29",
    "Date_Scraped": "2017-03-30",
    "Number_of_Games": "3,387",
    "Win_Percentage": "50.78%"
  },
  {
    "Champion_Name": "Yasuo",
    "Champion_Rank": "30",
    "Date_Scraped": "2017-03-30",
    "Number_of_Games": "5,578",
    "Win_Percentage": "50.66%"
  },
  {
    "Champion_Name": "Zyra",
    "Champion_Rank": "31",
    "Date_Scraped": "2017-03-30",
    "Number_of_Games": "2,881",
    "Win_Percentage": "50.64%"
  },
  {
    "Champion_Name": "Zilean",
    "Champion_Rank": "32",
    "Date_Scraped": "2017-03-30",
    "Number_of_Games": "1,126",
    "Win_Percentage": "50.62%"
  },
  {
    "Champion_Name": "Brand",
    "Champion_Rank": "33",
    "Date_Scraped": "2017-03-30",
    "Number_of_Games": "3,836",
    "Win_Percentage": "50.44%"
  },
  {
    "Champion_Name": "Singed",
    "Champion_Rank": "34",
    "Date_Scraped": "2017-03-30",
    "Number_of_Games": "1,131",
    "Win_Percentage": "50.40%"
  },
  {
    "Champion_Name": "Taric",
    "Champion_Rank": "35",
    "Date_Scraped": "2017-03-30",
    "Number_of_Games": "933",
    "Win_Percentage": "50.38%"
  },
  {
    "Champion_Name": "Anivia",
    "Champion_Rank": "36",
    "Date_Scraped": "2017-03-30",
    "Number_of_Games": "1,563",
    "Win_Percentage": "50.35%"
  },
  {
    "Champion_Name": "Twitch",
    "Champion_Rank": "37",
    "Date_Scraped": "2017-03-30",
    "Number_of_Games": "3,082",
    "Win_Percentage": "50.32%"
  },
  {
    "Champion_Name": "Miss Fortune",
    "Champion_Rank": "38",
    "Date_Scraped": "2017-03-30",
    "Number_of_Games": "4,542",
    "Win_Percentage": "50.15%"
  },
  {
    "Champion_Name": "Kled",
    "Champion_Rank": "39",
    "Date_Scraped": "2017-03-30",
    "Number_of_Games": "1,266",
    "Win_Percentage": "50.08%"
  },
  {
    "Champion_Name": "Karthus",
    "Champion_Rank": "40",
    "Date_Scraped": "2017-03-30",
    "Number_of_Games": "599",
    "Win_Percentage": "50.08%"
  },
  {
    "Champion_Name": "Darius",
    "Champion_Rank": "41",
    "Date_Scraped": "2017-03-30",
    "Number_of_Games": "4,211",
    "Win_Percentage": "50.06%"
  },
  {
    "Champion_Name": "Renekton",
    "Champion_Rank": "42",
    "Date_Scraped": "2017-03-30",
    "Number_of_Games": "3,286",
    "Win_Percentage": "50.03%"
  },
  {
    "Champion_Name": "Kog'Maw",
    "Champion_Rank": "43",
    "Date_Scraped": "2017-03-30",
    "Number_of_Games": "2,055",
    "Win_Percentage": "50.02%"
  },
  {
    "Champion_Name": "Graves",
    "Champion_Rank": "44",
    "Date_Scraped": "2017-03-30",
    "Number_of_Games": "5,764",
    "Win_Percentage": "49.98%"
  },
  {
    "Champion_Name": "Amumu",
    "Champion_Rank": "45",
    "Date_Scraped": "2017-03-30",
    "Number_of_Games": "1,944",
    "Win_Percentage": "49.95%"
  },
  {
    "Champion_Name": "Braum",
    "Champion_Rank": "46",
    "Date_Scraped": "2017-03-30",
    "Number_of_Games": "2,505",
    "Win_Percentage": "49.94%"
  },
  {
    "Champion_Name": "Annie",
    "Champion_Rank": "47",
    "Date_Scraped": "2017-03-30",
    "Number_of_Games": "3,435",
    "Win_Percentage": "49.93%"
  },
  {
    "Champion_Name": "Garen",
    "Champion_Rank": "48",
    "Date_Scraped": "2017-03-30",
    "Number_of_Games": "2,591",
    "Win_Percentage": "49.90%"
  },
  {
    "Champion_Name": "Pantheon",
    "Champion_Rank": "49",
    "Date_Scraped": "2017-03-30",
    "Number_of_Games": "2,307",
    "Win_Percentage": "49.89%"
  },
  {
    "Champion_Name": "Leona",
    "Champion_Rank": "50",
    "Date_Scraped": "2017-03-30",
    "Number_of_Games": "3,855",
    "Win_Percentage": "49.88%"
  },
  {
    "Champion_Name": "Tryndamere",
    "Champion_Rank": "51",
    "Date_Scraped": "2017-03-30",
    "Number_of_Games": "3,164",
    "Win_Percentage": "49.87%"
  },
  {
    "Champion_Name": "Lucian",
    "Champion_Rank": "52",
    "Date_Scraped": "2017-03-30",
    "Number_of_Games": "12,327",
    "Win_Percentage": "49.63%"
  },
  {
    "Champion_Name": "Nasus",
    "Champion_Rank": "53",
    "Date_Scraped": "2017-03-30",
    "Number_of_Games": "2,792",
    "Win_Percentage": "49.61%"
  },
  {
    "Champion_Name": "Vayne",
    "Champion_Rank": "54",
    "Date_Scraped": "2017-03-30",
    "Number_of_Games": "6,727",
    "Win_Percentage": "49.59%"
  },
  {
    "Champion_Name": "Shyvana",
    "Champion_Rank": "55",
    "Date_Scraped": "2017-03-30",
    "Number_of_Games": "1,381",
    "Win_Percentage": "49.46%"
  },
  {
    "Champion_Name": "Kayle",
    "Champion_Rank": "56",
    "Date_Scraped": "2017-03-30",
    "Number_of_Games": "1,235",
    "Win_Percentage": "49.39%"
  },
  {
    "Champion_Name": "Mordekaiser",
    "Champion_Rank": "57",
    "Date_Scraped": "2017-03-30",
    "Number_of_Games": "633",
    "Win_Percentage": "49.29%"
  },
  {
    "Champion_Name": "Jinx",
    "Champion_Rank": "58",
    "Date_Scraped": "2017-03-30",
    "Number_of_Games": "5,416",
    "Win_Percentage": "49.26%"
  },
  {
    "Champion_Name": "Irelia",
    "Champion_Rank": "59",
    "Date_Scraped": "2017-03-30",
    "Number_of_Games": "1,594",
    "Win_Percentage": "49.25%"
  },
  {
    "Champion_Name": "Kennen",
    "Champion_Rank": "60",
    "Date_Scraped": "2017-03-30",
    "Number_of_Games": "1,109",
    "Win_Percentage": "49.23%"
  },
  {
    "Champion_Name": "Nunu",
    "Champion_Rank": "61",
    "Date_Scraped": "2017-03-30",
    "Number_of_Games": "947",
    "Win_Percentage": "49.21%"
  },
  {
    "Champion_Name": "Lux",
    "Champion_Rank": "62",
    "Date_Scraped": "2017-03-30",
    "Number_of_Games": "5,780",
    "Win_Percentage": "49.15%"
  },
  {
    "Champion_Name": "Akali",
    "Champion_Rank": "63",
    "Date_Scraped": "2017-03-30",
    "Number_of_Games": "1,924",
    "Win_Percentage": "49.06%"
  },
  {
    "Champion_Name": "Katarina",
    "Champion_Rank": "64",
    "Date_Scraped": "2017-03-30",
    "Number_of_Games": "2,919",
    "Win_Percentage": "49.06%"
  },
  {
    "Champion_Name": "Poppy",
    "Champion_Rank": "65",
    "Date_Scraped": "2017-03-30",
    "Number_of_Games": "1,523",
    "Win_Percentage": "48.98%"
  },
  {
    "Champion_Name": "Malphite",
    "Champion_Rank": "66",
    "Date_Scraped": "2017-03-30",
    "Number_of_Games": "2,677",
    "Win_Percentage": "48.90%"
  },
  {
    "Champion_Name": "Aurelion Sol",
    "Champion_Rank": "67",
    "Date_Scraped": "2017-03-30",
    "Number_of_Games": "362",
    "Win_Percentage": "48.90%"
  },
  {
    "Champion_Name": "Tristana",
    "Champion_Rank": "68",
    "Date_Scraped": "2017-03-30",
    "Number_of_Games": "2,122",
    "Win_Percentage": "48.87%"
  },
  {
    "Champion_Name": "Fiora",
    "Champion_Rank": "69",
    "Date_Scraped": "2017-03-30",
    "Number_of_Games": "2,934",
    "Win_Percentage": "48.77%"
  },
  {
    "Champion_Name": "Jax",
    "Champion_Rank": "70",
    "Date_Scraped": "2017-03-30",
    "Number_of_Games": "3,266",
    "Win_Percentage": "48.71%"
  },
  {
    "Champion_Name": "Sivir",
    "Champion_Rank": "71",
    "Date_Scraped": "2017-03-30",
    "Number_of_Games": "1,315",
    "Win_Percentage": "48.67%"
  },
  {
    "Champion_Name": "Talon",
    "Champion_Rank": "72",
    "Date_Scraped": "2017-03-30",
    "Number_of_Games": "2,255",
    "Win_Percentage": "48.60%"
  },
  {
    "Champion_Name": "Lulu",
    "Champion_Rank": "73",
    "Date_Scraped": "2017-03-30",
    "Number_of_Games": "5,826",
    "Win_Percentage": "48.54%"
  },
  {
    "Champion_Name": "Ekko",
    "Champion_Rank": "74",
    "Date_Scraped": "2017-03-30",
    "Number_of_Games": "3,853",
    "Win_Percentage": "48.48%"
  },
  {
    "Champion_Name": "Riven",
    "Champion_Rank": "75",
    "Date_Scraped": "2017-03-30",
    "Number_of_Games": "3,518",
    "Win_Percentage": "48.47%"
  },
  {
    "Champion_Name": "Nautilus",
    "Champion_Rank": "76",
    "Date_Scraped": "2017-03-30",
    "Number_of_Games": "5,151",
    "Win_Percentage": "48.40%"
  },
  {
    "Champion_Name": "Ashe",
    "Champion_Rank": "77",
    "Date_Scraped": "2017-03-30",
    "Number_of_Games": "5,555",
    "Win_Percentage": "48.35%"
  },
  {
    "Champion_Name": "Orianna",
    "Champion_Rank": "78",
    "Date_Scraped": "2017-03-30",
    "Number_of_Games": "4,110",
    "Win_Percentage": "48.35%"
  },
  {
    "Champion_Name": "Morgana",
    "Champion_Rank": "79",
    "Date_Scraped": "2017-03-30",
    "Number_of_Games": "4,764",
    "Win_Percentage": "48.34%"
  },
  {
    "Champion_Name": "Caitlyn",
    "Champion_Rank": "80",
    "Date_Scraped": "2017-03-30",
    "Number_of_Games": "8,894",
    "Win_Percentage": "48.32%"
  },
  {
    "Champion_Name": "Rammus",
    "Champion_Rank": "81",
    "Date_Scraped": "2017-03-30",
    "Number_of_Games": "866",
    "Win_Percentage": "48.27%"
  },
  {
    "Champion_Name": "Hecarim",
    "Champion_Rank": "82",
    "Date_Scraped": "2017-03-30",
    "Number_of_Games": "3,238",
    "Win_Percentage": "48.27%"
  },
  {
    "Champion_Name": "Volibear",
    "Champion_Rank": "83",
    "Date_Scraped": "2017-03-30",
    "Number_of_Games": "1,206",
    "Win_Percentage": "48.09%"
  },
  {
    "Champion_Name": "Aatrox",
    "Champion_Rank": "84",
    "Date_Scraped": "2017-03-30",
    "Number_of_Games": "610",
    "Win_Percentage": "47.87%"
  },
  {
    "Champion_Name": "Taliyah",
    "Champion_Rank": "85",
    "Date_Scraped": "2017-03-30",
    "Number_of_Games": "861",
    "Win_Percentage": "47.85%"
  },
  {
    "Champion_Name": "Dr. Mundo",
    "Champion_Rank": "86",
    "Date_Scraped": "2017-03-30",
    "Number_of_Games": "961",
    "Win_Percentage": "47.76%"
  },
  {
    "Champion_Name": "Galio",
    "Champion_Rank": "87",
    "Date_Scraped": "2017-03-30",
    "Number_of_Games": "6,347",
    "Win_Percentage": "47.75%"
  },
  {
    "Champion_Name": "Diana",
    "Champion_Rank": "88",
    "Date_Scraped": "2017-03-30",
    "Number_of_Games": "1,605",
    "Win_Percentage": "47.60%"
  },
  {
    "Champion_Name": "Rumble",
    "Champion_Rank": "89",
    "Date_Scraped": "2017-03-30",
    "Number_of_Games": "1,762",
    "Win_Percentage": "47.56%"
  },
  {
    "Champion_Name": "Kindred",
    "Champion_Rank": "90",
    "Date_Scraped": "2017-03-30",
    "Number_of_Games": "1,205",
    "Win_Percentage": "47.55%"
  },
  {
    "Champion_Name": "Twisted Fate",
    "Champion_Rank": "91",
    "Date_Scraped": "2017-03-30",
    "Number_of_Games": "2,177",
    "Win_Percentage": "47.40%"
  },
  {
    "Champion_Name": "Viktor",
    "Champion_Rank": "92",
    "Date_Scraped": "2017-03-30",
    "Number_of_Games": "1,545",
    "Win_Percentage": "47.25%"
  },
  {
    "Champion_Name": "Tahm Kench",
    "Champion_Rank": "93",
    "Date_Scraped": "2017-03-30",
    "Number_of_Games": "1,107",
    "Win_Percentage": "47.06%"
  },
  {
    "Champion_Name": "Zed",
    "Champion_Rank": "94",
    "Date_Scraped": "2017-03-30",
    "Number_of_Games": "4,032",
    "Win_Percentage": "46.97%"
  },
  {
    "Champion_Name": "Varus",
    "Champion_Rank": "95",
    "Date_Scraped": "2017-03-30",
    "Number_of_Games": "1,695",
    "Win_Percentage": "46.96%"
  },
  {
    "Champion_Name": "Heimerdinger",
    "Champion_Rank": "96",
    "Date_Scraped": "2017-03-30",
    "Number_of_Games": "633",
    "Win_Percentage": "46.92%"
  },
  {
    "Champion_Name": "Gragas",
    "Champion_Rank": "97",
    "Date_Scraped": "2017-03-30",
    "Number_of_Games": "2,375",
    "Win_Percentage": "46.78%"
  },
  {
    "Champion_Name": "Udyr",
    "Champion_Rank": "98",
    "Date_Scraped": "2017-03-30",
    "Number_of_Games": "725",
    "Win_Percentage": "46.76%"
  },
  {
    "Champion_Name": "Cho'Gath",
    "Champion_Rank": "99",
    "Date_Scraped": "2017-03-30",
    "Number_of_Games": "1,927",
    "Win_Percentage": "46.76%"
  },
  {
    "Champion_Name": "Gangplank",
    "Champion_Rank": "100",
    "Date_Scraped": "2017-03-30",
    "Number_of_Games": "3,413",
    "Win_Percentage": "46.76%"
  },
  {
    "Champion_Name": "Vi",
    "Champion_Rank": "101",
    "Date_Scraped": "2017-03-30",
    "Number_of_Games": "2,636",
    "Win_Percentage": "46.59%"
  },
  {
    "Champion_Name": "Thresh",
    "Champion_Rank": "102",
    "Date_Scraped": "2017-03-30",
    "Number_of_Games": "8,250",
    "Win_Percentage": "46.51%"
  },
  {
    "Champion_Name": "Malzahar",
    "Champion_Rank": "103",
    "Date_Scraped": "2017-03-30",
    "Number_of_Games": "2,398",
    "Win_Percentage": "46.50%"
  },
  {
    "Champion_Name": "Shen",
    "Champion_Rank": "104",
    "Date_Scraped": "2017-03-30",
    "Number_of_Games": "2,163",
    "Win_Percentage": "46.42%"
  },
  {
    "Champion_Name": "Rengar",
    "Champion_Rank": "105",
    "Date_Scraped": "2017-03-30",
    "Number_of_Games": "2,138",
    "Win_Percentage": "46.40%"
  },
  {
    "Champion_Name": "Gnar",
    "Champion_Rank": "106",
    "Date_Scraped": "2017-03-30",
    "Number_of_Games": "1,290",
    "Win_Percentage": "46.36%"
  },
  {
    "Champion_Name": "Vladimir",
    "Champion_Rank": "107",
    "Date_Scraped": "2017-03-30",
    "Number_of_Games": "2,804",
    "Win_Percentage": "46.22%"
  },
  {
    "Champion_Name": "Trundle",
    "Champion_Rank": "108",
    "Date_Scraped": "2017-03-30",
    "Number_of_Games": "1,153",
    "Win_Percentage": "46.05%"
  },
  {
    "Champion_Name": "Kalista",
    "Champion_Rank": "109",
    "Date_Scraped": "2017-03-30",
    "Number_of_Games": "1,189",
    "Win_Percentage": "46.01%"
  },
  {
    "Champion_Name": "Jhin",
    "Champion_Rank": "110",
    "Date_Scraped": "2017-03-30",
    "Number_of_Games": "5,186",
    "Win_Percentage": "45.93%"
  },
  {
    "Champion_Name": "Kha'Zix",
    "Champion_Rank": "111",
    "Date_Scraped": "2017-03-30",
    "Number_of_Games": "2,528",
    "Win_Percentage": "45.93%"
  },
  {
    "Champion_Name": "Lee Sin",
    "Champion_Rank": "112",
    "Date_Scraped": "2017-03-30",
    "Number_of_Games": "8,413",
    "Win_Percentage": "45.63%"
  },
  {
    "Champion_Name": "Ezreal",
    "Champion_Rank": "113",
    "Date_Scraped": "2017-03-30",
    "Number_of_Games": "9,239",
    "Win_Percentage": "45.61%"
  },
  {
    "Champion_Name": "Karma",
    "Champion_Rank": "114",
    "Date_Scraped": "2017-03-30",
    "Number_of_Games": "2,968",
    "Win_Percentage": "45.52%"
  },
  {
    "Champion_Name": "Elise",
    "Champion_Rank": "115",
    "Date_Scraped": "2017-03-30",
    "Number_of_Games": "1,441",
    "Win_Percentage": "45.45%"
  },
  {
    "Champion_Name": "Cassiopeia",
    "Champion_Rank": "116",
    "Date_Scraped": "2017-03-30",
    "Number_of_Games": "1,029",
    "Win_Percentage": "45.38%"
  },
  {
    "Champion_Name": "Kassadin",
    "Champion_Rank": "117",
    "Date_Scraped": "2017-03-30",
    "Number_of_Games": "995",
    "Win_Percentage": "45.23%"
  },
  {
    "Champion_Name": "Olaf",
    "Champion_Rank": "118",
    "Date_Scraped": "2017-03-30",
    "Number_of_Games": "1,526",
    "Win_Percentage": "44.95%"
  },
  {
    "Champion_Name": "Quinn",
    "Champion_Rank": "119",
    "Date_Scraped": "2017-03-30",
    "Number_of_Games": "1,024",
    "Win_Percentage": "44.82%"
  },
  {
    "Champion_Name": "Camille",
    "Champion_Rank": "120",
    "Date_Scraped": "2017-03-30",
    "Number_of_Games": "1,608",
    "Win_Percentage": "44.78%"
  },
  {
    "Champion_Name": "Evelynn",
    "Champion_Rank": "121",
    "Date_Scraped": "2017-03-30",
    "Number_of_Games": "1,651",
    "Win_Percentage": "44.64%"
  },
  {
    "Champion_Name": "Syndra",
    "Champion_Rank": "122",
    "Date_Scraped": "2017-03-30",
    "Number_of_Games": "1,950",
    "Win_Percentage": "44.56%"
  },
  {
    "Champion_Name": "Alistar",
    "Champion_Rank": "123",
    "Date_Scraped": "2017-03-30",
    "Number_of_Games": "1,579",
    "Win_Percentage": "44.33%"
  },
  {
    "Champion_Name": "Rek'Sai",
    "Champion_Rank": "124",
    "Date_Scraped": "2017-03-30",
    "Number_of_Games": "368",
    "Win_Percentage": "44.29%"
  },
  {
    "Champion_Name": "Lissandra",
    "Champion_Rank": "125",
    "Date_Scraped": "2017-03-30",
    "Number_of_Games": "675",
    "Win_Percentage": "43.85%"
  },
  {
    "Champion_Name": "Bard",
    "Champion_Rank": "126",
    "Date_Scraped": "2017-03-30",
    "Number_of_Games": "1,330",
    "Win_Percentage": "43.76%"
  },
  {
    "Champion_Name": "Urgot",
    "Champion_Rank": "127",
    "Date_Scraped": "2017-03-30",
    "Number_of_Games": "248",
    "Win_Percentage": "43.55%"
  },
  {
    "Champion_Name": "Jayce",
    "Champion_Rank": "128",
    "Date_Scraped": "2017-03-30",
    "Number_of_Games": "1,785",
    "Win_Percentage": "43.47%"
  },
  {
    "Champion_Name": "Azir",
    "Champion_Rank": "129",
    "Date_Scraped": "2017-03-30",
    "Number_of_Games": "589",
    "Win_Percentage": "42.95%"
  },
  {
    "Champion_Name": "Maokai",
    "Champion_Rank": "130",
    "Date_Scraped": "2017-03-30",
    "Number_of_Games": "956",
    "Win_Percentage": "42.89%"
  },
  {
    "Champion_Name": "Nidalee",
    "Champion_Rank": "131",
    "Date_Scraped": "2017-03-30",
    "Number_of_Games": "928",
    "Win_Percentage": "42.24%"
  },
  {
    "Champion_Name": "Ryze",
    "Champion_Rank": "132",
    "Date_Scraped": "2017-03-30",
    "Number_of_Games": "887",
    "Win_Percentage": "42.16%"
  },
  {
    "Champion_Name": "LeBlanc",
    "Champion_Rank": "133",
    "Date_Scraped": "2017-03-30",
    "Number_of_Games": "718",
    "Win_Percentage": "40.53%"
  },
  {
    "Champion_Name": "Corki",
    "Champion_Rank": "134",
    "Date_Scraped": "2017-03-30",
    "Number_of_Games": "411",
    "Win_Percentage": "40.39%"
  }
]